cjdb/__init__.py
cjdb/cli.py
cjdb/logger.py
cjdb/model/BASICQUERIES.md
cjdb/model/README.md
cjdb/model/__init__.py
cjdb/model/sqlalchemy_models/__init__.py
cjdb/model/uml.png
cjdb/modules/__init__.py
cjdb/modules/checks.py
cjdb/modules/exceptions.py
cjdb/modules/exporter.py
cjdb/modules/extensions.py
cjdb/modules/geometric.py
cjdb/modules/importer.py
cjdb/modules/utils.py
cjdb/resources/__init__.py
cjdb/resources/object_types.py
cjdb/resources/post_import.sql
cjdb/resources/strings.py
cjdb-2.1.0.dist-info/LICENSE
cjdb-2.1.0.dist-info/WHEEL
cjdb-2.1.0.dist-info/entry_points.txt
cjdb-2.1.0.dist-info/METADATA
cjdb-2.1.0.dist-info/RECORD
