Metadata-Version: 2.1
Name: cjdb
Version: 2.1.0
Summary: CJDB is a tool that enables CityJSON integration with a PostgreSQL database
Home-page: https://github.com/tudelft3d/cjdb
License: MIT
Keywords: CityJSON,PostgreSQL
Author: Cynthia Cai
Maintainer: Gina Stavropoulou
Maintainer-email: g.stavropoulou@tudelft.nl
Requires-Python: >=3.8.1,<4.0.0
Classifier: License :: OSI Approved :: MIT License
Classifier: Programming Language :: Python :: 3
Classifier: Programming Language :: Python :: 3.9
Classifier: Programming Language :: Python :: 3.10
Classifier: Programming Language :: Python :: 3.11
Requires-Dist: cjio (>=0.9,<0.10)
Requires-Dist: geoalchemy2 (>=0.13.1,<0.14.0)
Requires-Dist: numpy (>=1.24.2,<2.0.0)
Requires-Dist: psycopg2-binary (>=2.9.6,<3.0.0)
Requires-Dist: pyproj (>=3.5.0,<4.0.0)
Requires-Dist: requests (>=2.28.2,<3.0.0)
Requires-Dist: shapely (>=2.0.1,<3.0.0)
Project-URL: Repository, https://github.com/tudelft3d/cjdb
